fastaai/__init__.py
fastaai/protein_pred_and_HMM_search.py
fastaai_preproc-0.3.dist-info/LICENSE
fastaai_preproc-0.3.dist-info/METADATA
fastaai_preproc-0.3.dist-info/WHEEL
fastaai_preproc-0.3.dist-info/entry_points.txt
fastaai_preproc-0.3.dist-info/top_level.txt
fastaai_preproc-0.3.dist-info/RECORD
