Metadata-Version: 2.1
Name: fastaai-preproc
Version: 0.3
Summary: Protein predictions and HMM searches
Author: Kenji Gerhardt
Author-email: kenji.gerhardt@gmail.com
Requires-Python: >=3
License-File: LICENSE
Requires-Dist: pyrodigal
Requires-Dist: pyhmmer
